qg_toolkit/__init__.py
qg_toolkit/cf_turnstile/__init__.py
qg_toolkit/cf_turnstile/cf_turnstile.py
qg_toolkit/cf_turnstile/fastapi_client.py
qg_toolkit/cf_turnstile/test.py
qg_toolkit/geetest_captcha/__init__.py
qg_toolkit/geetest_captcha/geetest4_fullpage/__init__.py
qg_toolkit/geetest_captcha/geetest4_fullpage/geetest_v4.py
qg_toolkit/geetest_captcha/geetest4_fullpage/jiyan.js
qg_toolkit/geetest_captcha/geetest4_fullpage/mian.py
qg_toolkit/geetest_captcha/geetest4_slide/__init__.py
qg_toolkit/geetest_captcha/geetest4_slide/gap.py
qg_toolkit/geetest_captcha/geetest4_slide/geetest_slide_v4.py
qg_toolkit/geetest_captcha/geetest4_slide/img/bg.png
qg_toolkit/geetest_captcha/geetest4_slide/img/show_image.png
qg_toolkit/geetest_captcha/geetest4_slide/img/slide.png
qg_toolkit/geetest_captcha/geetest4_slide/img/tracks.json
qg_toolkit/geetest_captcha/geetest4_slide/jiyan.js
qg_toolkit/geetest_captcha/geetest4_slide/mian.py
qg_toolkit/geetest_captcha/geetest4_slide/trace.py
qg_toolkit/qgalxe/galxe.py
qg_toolkit/qgalxe/GeetestFullPageV4.py
qg_toolkit/qgalxe/GeetestFullPageV4_1.py
qg_toolkit/qgalxe/GeetestSlideV4.py
qg_toolkit/recaptcha/__init__.py
qg_toolkit/recaptcha/recaptcha_client.py
qg_toolkit/recaptcha/test.py
qg_toolkit/test/demo.yaml
qg_toolkit/test/sol钱包.txt
qg_toolkit/test/test.py
qg_toolkit/test/test2.py
qg_toolkit/test/test3.py
qg_toolkit/test/test4.py
qg_toolkit/test/ton钱包.txt
qg_toolkit/tools/__init__.py
qg_toolkit/tools/cui_qiu_client.py
qg_toolkit/tools/date_util.py
qg_toolkit/tools/discord.py
qg_toolkit/tools/qg_airdrop.py
qg_toolkit/tools/qg_aptos.py
qg_toolkit/tools/qg_btc.py
qg_toolkit/tools/qg_cosmos.py
qg_toolkit/tools/qg_crypto.py
qg_toolkit/tools/qg_eth.py
qg_toolkit/tools/qg_file.py
qg_toolkit/tools/qg_Invite_mgr.py
qg_toolkit/tools/qg_log.py
qg_toolkit/tools/qg_models.py
qg_toolkit/tools/qg_random.py
qg_toolkit/tools/qg_solana.py
qg_toolkit/tools/qg_starknet.py
qg_toolkit/tools/qg_ton.py
qg_toolkit/tools/QGAirdrop.sol
qg_toolkit/tools/QGSui.py
qg_toolkit-1.1.25.dist-info/METADATA
qg_toolkit-1.1.25.dist-info/WHEEL
qg_toolkit-1.1.25.dist-info/RECORD
