Metadata-Version: 2.3
Name: qg_toolkit
Version: 1.1.25
Summary: qg_toolkit for Python!
Author: qg
Author-email: qg@gmail.com
Requires-Python: >=3.9,<4.0
Classifier: Programming Language :: Python :: 3
Classifier: Programming Language :: Python :: 3.9
Classifier: Programming Language :: Python :: 3.10
Classifier: Programming Language :: Python :: 3.11
Classifier: Programming Language :: Python :: 3.12
Classifier: Programming Language :: Python :: 3.13
Requires-Dist: ImageHash (>=4.3.1,<5.0.0)
Requires-Dist: PySocks (>=1.7.1,<2.0.0)
Requires-Dist: PyYAML (>=6.0.1,<7.0.0)
Requires-Dist: aiohttp (>=3.9,<4.0)
Requires-Dist: aptos_sdk (>=0.8.6,<0.9.0)
Requires-Dist: base58 (>=2.1.1,<3.0.0)
Requires-Dist: beautifulsoup4 (>=4,<5)
Requires-Dist: bech32 (>=1.2.0,<2.0.0)
Requires-Dist: bip_utils (>=2.9.3,<3.0.0)
Requires-Dist: capsolver (>=1.0.7,<2.0.0)
Requires-Dist: curl-cffi (>=0.7.1,<0.8.0)
Requires-Dist: faker (>=24.11.0,<25.0.0)
Requires-Dist: fastapi (>=0.115.7,<0.116.0)
Requires-Dist: flask (>=3.0.3,<4.0.0)
Requires-Dist: gevent (>=24.2.1,<25.0.0)
Requires-Dist: loguru (>=0.7,<0.8)
Requires-Dist: lxml (>=5,<6)
Requires-Dist: mnemonic (>=0.21,<0.22)
Requires-Dist: pillow (>=10.3.0,<11.0.0)
Requires-Dist: playwright (==1.43.0)
Requires-Dist: portalocker (>=3.1.1,<4.0.0)
Requires-Dist: pycryptodome (>=3.20.0,<4.0.0)
Requires-Dist: pydantic (>=2,<3)
Requires-Dist: pynacl (>=1.5.0,<2.0.0)
Requires-Dist: pyotp (>=2,<3)
Requires-Dist: requests (>=2,<3)
Requires-Dist: retry (>=0.9.2,<0.10.0)
Requires-Dist: rsa (>=4.9,<5.0)
Requires-Dist: solana (>=0.34.2,<0.35.0)
Requires-Dist: solders (>=0.21.0,<0.22.0)
Requires-Dist: tenacity (>=8,<9)
Requires-Dist: tonsdk (>=1.0.15,<2.0.0)
Requires-Dist: tqdm (>=4.66.5,<5.0.0)
Requires-Dist: uvicorn (>=0.34.0,<0.35.0)
Requires-Dist: web3 (>=6.17.2,<7.0.0)
Requires-Dist: websockets (==11.0.3)
Requires-Dist: yarl (>=1,<2)
